rec_sdk/__init__.py
rec_sdk/test.py
rec_sdk-0.1.0.dist-info/METADATA
rec_sdk-0.1.0.dist-info/RECORD
rec_sdk-0.1.0.dist-info/WHEEL
rec_sdk-0.1.0.dist-info/top_level.txt
