Metadata-Version: 2.1
Name: rec-sdk
Version: 0.1.0
Summary: wimi sdk for recommendation
Home-page: https://wimigitlab.git
Author: Sun Xuen
License: MIT
Platform: UNKNOWN
Requires-Python: >=3.6.0
